SitanfuCs183fYcChuangyeKe2017ZhongwenBiji/README.md
SitanfuCs183fYcChuangyeKe2017ZhongwenBiji/__init__.py
SitanfuCs183fYcChuangyeKe2017ZhongwenBiji/__main__.py
SitanfuCs183fYcChuangyeKe2017ZhongwenBiji/file.epub
SitanfuCs183fYcChuangyeKe2017ZhongwenBiji/index.html
SitanfuCs183fYcChuangyeKe2017ZhongwenBiji/css/__init__.py
SitanfuCs183fYcChuangyeKe2017ZhongwenBiji/css/annotations.css
SitanfuCs183fYcChuangyeKe2017ZhongwenBiji/css/main.css
SitanfuCs183fYcChuangyeKe2017ZhongwenBiji/css/normalize.css
SitanfuCs183fYcChuangyeKe2017ZhongwenBiji/css/popup.css
SitanfuCs183fYcChuangyeKe2017ZhongwenBiji/font/__init__.py
SitanfuCs183fYcChuangyeKe2017ZhongwenBiji/font/fontello.eot
SitanfuCs183fYcChuangyeKe2017ZhongwenBiji/font/fontello.svg
SitanfuCs183fYcChuangyeKe2017ZhongwenBiji/font/fontello.ttf
SitanfuCs183fYcChuangyeKe2017ZhongwenBiji/font/fontello.woff
SitanfuCs183fYcChuangyeKe2017ZhongwenBiji/img/__init__.py
SitanfuCs183fYcChuangyeKe2017ZhongwenBiji/img/annotator-glyph-sprite.png
SitanfuCs183fYcChuangyeKe2017ZhongwenBiji/img/annotator-icon-sprite.png
SitanfuCs183fYcChuangyeKe2017ZhongwenBiji/img/apple-touch-icon.png
SitanfuCs183fYcChuangyeKe2017ZhongwenBiji/img/cancelfullscreen.png
SitanfuCs183fYcChuangyeKe2017ZhongwenBiji/img/close.png
SitanfuCs183fYcChuangyeKe2017ZhongwenBiji/img/fullscreen.png
SitanfuCs183fYcChuangyeKe2017ZhongwenBiji/img/loader.gif
SitanfuCs183fYcChuangyeKe2017ZhongwenBiji/img/menu-icon.png
SitanfuCs183fYcChuangyeKe2017ZhongwenBiji/img/save.png
SitanfuCs183fYcChuangyeKe2017ZhongwenBiji/img/saved.png
SitanfuCs183fYcChuangyeKe2017ZhongwenBiji/img/settings-s.png
SitanfuCs183fYcChuangyeKe2017ZhongwenBiji/img/settings.png
SitanfuCs183fYcChuangyeKe2017ZhongwenBiji/img/star.png
SitanfuCs183fYcChuangyeKe2017ZhongwenBiji/js/__init__.py
SitanfuCs183fYcChuangyeKe2017ZhongwenBiji/js/epub.js
SitanfuCs183fYcChuangyeKe2017ZhongwenBiji/js/epub.min.js
SitanfuCs183fYcChuangyeKe2017ZhongwenBiji/js/epub.min.map
SitanfuCs183fYcChuangyeKe2017ZhongwenBiji/js/hooks.min.js
sitanfu_cs183f_yc_chuangye_ke_2017_zhongwen_biji-2024.3.3.0.dist-info/METADATA
sitanfu_cs183f_yc_chuangye_ke_2017_zhongwen_biji-2024.3.3.0.dist-info/WHEEL
sitanfu_cs183f_yc_chuangye_ke_2017_zhongwen_biji-2024.3.3.0.dist-info/entry_points.txt
sitanfu_cs183f_yc_chuangye_ke_2017_zhongwen_biji-2024.3.3.0.dist-info/top_level.txt
sitanfu_cs183f_yc_chuangye_ke_2017_zhongwen_biji-2024.3.3.0.dist-info/RECORD
